solaxcloud/__init__.py
solaxcloud/solaxcloud.py
solaxcloud-0.1.0.dist-info/LICENSE
solaxcloud-0.1.0.dist-info/METADATA
solaxcloud-0.1.0.dist-info/WHEEL
solaxcloud-0.1.0.dist-info/top_level.txt
solaxcloud-0.1.0.dist-info/RECORD
