Metadata-Version: 2.1
Name: solaxcloud
Version: 0.1.0
Summary: API wrapper for solax cloud
Home-page: https://github.com/frank8the9tank/SolaxCloud
Author: Frank van der Heide
Author-email: frankvanderheide89@gmail.com
Classifier: Programming Language :: Python :: 3
Classifier: License :: OSI Approved :: MIT License
Classifier: Operating System :: OS Independent
License-File: LICENSE
